setup.py
directapi/__init__.py
ya_direct_api.egg-info/PKG-INFO
ya_direct_api.egg-info/SOURCES.txt
ya_direct_api.egg-info/dependency_links.txt
ya_direct_api.egg-info/not-zip-safe
ya_direct_api.egg-info/top_level.txt