Metadata-Version: 1.0
Name: ya-direct-api
Version: 0.1
Summary: Yandex Direct API Wrapper
Home-page: https://github.com/amureki/ya-direct-api.git
Author: Rustem Sayargaliev
Author-email: r.sayargaliev@gmail.com
License: MIT
Platform: UNKNOWN
